vector_db_cost_inspector-0.1.5.dist-info/licenses/LICENSE
vector_db_inspector/__init__.py
vector_db_inspector/main.py
vector_db_inspector/cost_inspector/__init__.py
vector_db_inspector/cost_inspector/interactive_auditor.py
vector_db_inspector/cost_inspector/real_inspector.py
vector_db_inspector/cost_inspector/utilities.py
vector_db_cost_inspector-0.1.5.dist-info/METADATA
vector_db_cost_inspector-0.1.5.dist-info/WHEEL
vector_db_cost_inspector-0.1.5.dist-info/entry_points.txt
vector_db_cost_inspector-0.1.5.dist-info/top_level.txt
vector_db_cost_inspector-0.1.5.dist-info/RECORD
