Metadata-Version: 2.4
Name: vector-db-cost-inspector
Version: 0.1.5
Summary: Inspector for Vector DB cost saving
Author-email: BillyCPH <billychenph@email.com>
Project-URL: Homepage, https://github.com/billycph/VectorDBCostSavingInspector
Requires-Python: >=3.7
License-File: LICENSE
Requires-Dist: pinecone>=5.1.0
Requires-Dist: boto3>=1.34.0
Requires-Dist: pandas>=2.1.0
Requires-Dist: pyarrow>=14.0.0
Requires-Dist: python-dotenv>=1.0.0
Dynamic: license-file
